Workbook

Sheet Laporan
A1: General Ledger | F1: AJP | K1: Neraca Saldo (Balance Sheet)
A2: Tanggal | B2: Nama Akun | C2: Debit | D2: Credit | F2: Tanggal | G2: Nama Akun | H2: Debit | I2: Kredit | K2: Periode Akhir Jan 2017
A3: 46023 | B3: Kas | C3: 20000000 | F3: 46387 | G3: Beban Sewa | H3: 3000000 | K3: Aktiva(Assets) | N3: Passiva
B4: Modal | D4: 20000000 | G4: Sewa dibayar dimuka | I4: 3000000 | K4: Aktiva Lancar | N4: Hutang
A5: 46024 | B5: Peralatan | C5: 3000000 | F5: 46387 | G5: Beban Asuransi | H5: 5000000 | K5: Kas | L5: =G43 -> 23500000 | N5: Hutang Lancar
B6: Perlengkapan | C6: 500000 | G6: Asuransi dibayar dimuka | I6: 5000000 | K6: Piutang | L6: =G48 -> 3000000 | N6: Hutang Usaha | O6: =H50 -> 1000000
B7: Kas | D7: =C5+C6 -> 3500000 | F7: 46387 | G7: Pendapatan diterima dimuka | H7: 4000000 | K7: Perlengkapan | L7: =G46 -> 1200000 | N7: Pendapatan Diterima Dimuka | O7: =H55 -> 8000000
B8: Sewa Dibayar Dimuka | C8: 3000000 | G8: Pendapatan | I8: 4000000 | K8: Asuransi Dibayar Dimuka | L8: =G54 -> 7000000 | N8: Hutang Gaji | O8: =H58 -> 3500000
B9: Kas | D9: 3000000 | F9: 46387 | G9: Beban Gaji | H9: 3500000 | K9: Sewa Dibayar Dimuka | L9: =G47 -> 0 | N9: Hutang Jangka Panjang
A10: 46025 | B10: Piutang | C10: 5000000 | G10: Hutang Gaji | I10: 3500000 | K10: Total Aktiva Lancar | M10: =SUM(L5:L9) -> 34700000 | N10: Hutang Bank | O10: 0
B11: Pendapatan | D11: 5000000 | F11: 46387 | G11: Beban penyusutan peralatan | H11: ='Perincian Laporan'!C9 -> 600000 | K11: Aktiva Tetap | N11: Total Utang | P11: =SUM(O5:O10) -> 12500000
A12: 46028 | B12: Piutang | C12: 3000000 | G12: Akumulasi penyusutan peralatan | I12: ='Perincian Laporan'!C9 -> 600000 | K12: Tanah
B13: Pendapatan | D13: 3000000 | F13: 46387 | G13: Beban Perlengkapan | H13: ='Perincian Laporan'!C17-'Perincian Laporan'!C18 -> 1300000 | K13: Bangunan | N13: Modal | P13: =C80 -> 24600000
A14: 46029 | B14: Perlengkapan | C14: 1000000 | G14: Perlengkapan | I14: ='Perincian Laporan'!C17-'Perincian Laporan'!C18 -> 1300000 | K14: Akumulasi Penyusutan Bangunan
B15: Hutang | D15: 1000000 | K15: Peralatan | L15: =G45 -> 3000000
A16: 46031 | B16: Piutang | C16: 9000000 | K16: Akumulasi Penyusutan Peralatan | M16: =-H60 -> -600000
B17: Pendapatan | D17: 9000000 | K17: Total Aktiva Tetap | M17: =SUM(SUM(L12:L16),SUM(M12:M16)) -> 2400000
B18: Kas | C18: 3000000 | K18: Total Aktiva | M18: =M10+M17 -> 37100000 | N18: Total Utang & Modal | P18: =P11+P13 -> 37100000
B19: Piutang | D19: 3000000
A20: 46043 | B20: Kas | C20: 4000000
B21: Pendapatan | D21: 4000000
A22: 46044 | B22: Kas | C22: 5000000
B23: Piutang | D23: 5000000
A24: 46045 | B24: Perlengkapan | C24: 1000000
B25: Kas | D25: 1000000
A26: 46046 | B26: Kas | C26: 6000000
B27: Piutang | D27: 6000000
A28: 46047 | B28: Beban Gaji | C28: 3000000
B29: Kas | D29: 3000000
A30: 46048 | B30: Prive | C30: 1500000
B31: Kas | D31: 1500000
A32: 46050 | B32: Beban Utilitas | C32: 2500000
B33: Kas | D33: 2500000
A34: 46235 | B34: Asuransi Dibayar Dimuka | C34: 12000000
B35: Kas | D35: 12000000
A36: 46266 | B36: Kas | C36: 12000000
B37: Pendapatan Diterima Dimuka | D37: 12000000
A38: Total | C38: =SUM(C2:C37) -> 94500000 | D38: =SUM(D2:D37) -> 94500000
B40: Trial Balance
B41: Nama Akun | C41: Jurnal Umum | E41: Ayat Jurnal Penyesuaian | G41: Saldo Akhir
C42: Debit | D42: Kredit | E42: Debit | F42: Kredit | G42: Debit | H42: Kredit
B43: {=_xlfn.UNIQUE(_xlfn.VSTACK(B3:B37,G3:G14))} -> Kas | C43: =SUMIF($B$3:$B$37,B43,$C$3:$C$37) -> 50000000 | D43: =SUMIF($B$3:$B$37,B43,$D$3:$D$37) -> 26500000 | E43: =SUMIF($G$3:$G$14,$B43,$H$3:$H$14) -> 0 | F43: =SUMIF($G$3:$G$14,B43,$I$3:$I$14) -> 0 | G43: =(C43+E43)-(D43+F43) -> 23500000 | H43: 0
B44: Modal | C44: =SUMIF($B$3:$B$37,B44,$C$3:$C$37) -> 0 | D44: =SUMIF($B$3:$B$37,B44,$D$3:$D$37) -> 20000000 | E44: =SUMIF($G$3:$G$14,$B44,$H$3:$H$14) -> 0 | F44: =SUMIF($G$3:$G$14,B44,$I$3:$I$14) -> 0 | G44: 0 | H44: =(D44+F44)-C44+E44 -> 20000000
B45: Peralatan | C45: =SUMIF($B$3:$B$37,B45,$C$3:$C$37) -> 3000000 | D45: =SUMIF($B$3:$B$37,B45,$D$3:$D$37) -> 0 | E45: =SUMIF($G$3:$G$14,$B45,$H$3:$H$14) -> 0 | F45: =SUMIF($G$3:$G$14,B45,$I$3:$I$14) -> 0 | G45: =(C45+E45)-(D45+F45) -> 3000000 | H45: 0
B46: Perlengkapan | C46: =SUMIF($B$3:$B$37,B46,$C$3:$C$37) -> 2500000 | D46: =SUMIF($B$3:$B$37,B46,$D$3:$D$37) -> 0 | E46: =SUMIF($G$3:$G$14,$B46,$H$3:$H$14) -> 0 | F46: =SUMIF($G$3:$G$14,B46,$I$3:$I$14) -> 1300000 | G46: =(C46+E46)-(D46+F46) -> 1200000 | H46: 0
B47: Sewa Dibayar Dimuka | C47: =SUMIF($B$3:$B$37,B47,$C$3:$C$37) -> 3000000 | D47: =SUMIF($B$3:$B$37,B47,$D$3:$D$37) -> 0 | E47: =SUMIF($G$3:$G$14,$B47,$H$3:$H$14) -> 0 | F47: =SUMIF($G$3:$G$14,B47,$I$3:$I$14) -> 3000000 | G47: =(C47+E47)-(D47+F47) -> 0 | H47: =(D47+F47)-C47+E47 -> 0
B48: Piutang | C48: =SUMIF($B$3:$B$37,B48,$C$3:$C$37) -> 17000000 | D48: =SUMIF($B$3:$B$37,B48,$D$3:$D$37) -> 14000000 | E48: =SUMIF($G$3:$G$14,$B48,$H$3:$H$14) -> 0 | F48: =SUMIF($G$3:$G$14,B48,$I$3:$I$14) -> 0 | G48: =(C48+E48)-(D48+F48) -> 3000000 | H48: 0
B49: Pendapatan | C49: =SUMIF($B$3:$B$37,B49,$C$3:$C$37) -> 0 | D49: =SUMIF($B$3:$B$37,B49,$D$3:$D$37) -> 21000000 | E49: =SUMIF($G$3:$G$14,$B49,$H$3:$H$14) -> 0 | F49: =SUMIF($G$3:$G$14,B49,$I$3:$I$14) -> 4000000 | G49: 0 | H49: =(D49+F49)-C49+E49 -> 25000000
B50: Hutang | C50: =SUMIF($B$3:$B$37,B50,$C$3:$C$37) -> 0 | D50: =SUMIF($B$3:$B$37,B50,$D$3:$D$37) -> 1000000 | E50: =SUMIF($G$3:$G$14,$B50,$H$3:$H$14) -> 0 | F50: =SUMIF($G$3:$G$14,B50,$I$3:$I$14) -> 0 | G50: 0 | H50: =(D50+F50)-C50+E50 -> 1000000
B51: Beban Gaji | C51: =SUMIF($B$3:$B$37,B51,$C$3:$C$37) -> 3000000 | D51: =SUMIF($B$3:$B$37,B51,$D$3:$D$37) -> 0 | E51: =SUMIF($G$3:$G$14,$B51,$H$3:$H$14) -> 3500000 | F51: =SUMIF($G$3:$G$14,B51,$I$3:$I$14) -> 0 | G51: =(C51+E51)-(D51+F51) -> 6500000 | H51: 0
B52: Prive | C52: =SUMIF($B$3:$B$37,B52,$C$3:$C$37) -> 1500000 | D52: =SUMIF($B$3:$B$37,B52,$D$3:$D$37) -> 0 | E52: =SUMIF($G$3:$G$14,$B52,$H$3:$H$14) -> 0 | F52: =SUMIF($G$3:$G$14,B52,$I$3:$I$14) -> 0 | G52: =(C52+E52)-(D52+F52) -> 1500000 | H52: 0
B53: Beban Utilitas | C53: =SUMIF($B$3:$B$37,B53,$C$3:$C$37) -> 2500000 | D53: =SUMIF($B$3:$B$37,B53,$D$3:$D$37) -> 0 | E53: =SUMIF($G$3:$G$14,$B53,$H$3:$H$14) -> 0 | F53: =SUMIF($G$3:$G$14,B53,$I$3:$I$14) -> 0 | G53: =(C53+E53)-(D53+F53) -> 2500000 | H53: 0
B54: Asuransi Dibayar Dimuka | C54: =SUMIF($B$3:$B$37,B54,$C$3:$C$37) -> 12000000 | D54: =SUMIF($B$3:$B$37,B54,$D$3:$D$37) -> 0 | E54: =SUMIF($G$3:$G$14,$B54,$H$3:$H$14) -> 0 | F54: =SUMIF($G$3:$G$14,B54,$I$3:$I$14) -> 5000000 | G54: =(C54+E54)-(D54+F54) -> 7000000 | H54: 0
B55: Pendapatan Diterima Dimuka | C55: =SUMIF($B$3:$B$37,B55,$C$3:$C$37) -> 0 | D55: =SUMIF($B$3:$B$37,B55,$D$3:$D$37) -> 12000000 | E55: =SUMIF($G$3:$G$14,$B55,$H$3:$H$14) -> 4000000 | F55: =SUMIF($G$3:$G$14,B55,$I$3:$I$14) -> 0 | G55: 0 | H55: =(D55+F55)-(C55+E55) -> 8000000
B56: Beban Sewa | C56: =SUMIF($B$3:$B$37,B56,$C$3:$C$37) -> 0 | D56: =SUMIF($B$3:$B$37,B56,$D$3:$D$37) -> 0 | E56: =SUMIF($G$3:$G$14,$B56,$H$3:$H$14) -> 3000000 | F56: =SUMIF($G$3:$G$14,B56,$I$3:$I$14) -> 0 | G56: =(C56+E56)-(D56+F56) -> 3000000 | H56: 0
B57: Beban Asuransi | C57: =SUMIF($B$3:$B$37,B57,$C$3:$C$37) -> 0 | D57: =SUMIF($B$3:$B$37,B57,$D$3:$D$37) -> 0 | E57: =SUMIF($G$3:$G$14,$B57,$H$3:$H$14) -> 5000000 | F57: =SUMIF($G$3:$G$14,B57,$I$3:$I$14) -> 0 | G57: =(C57+E57)-(D57+F57) -> 5000000 | H57: 0
B58: Hutang Gaji | C58: =SUMIF($B$3:$B$37,B58,$C$3:$C$37) -> 0 | D58: =SUMIF($B$3:$B$37,B58,$D$3:$D$37) -> 0 | E58: =SUMIF($G$3:$G$14,$B58,$H$3:$H$14) -> 0 | F58: =SUMIF($G$3:$G$14,B58,$I$3:$I$14) -> 3500000 | G58: 0 | H58: =(D58+F58)-C58+E58 -> 3500000
B59: Beban penyusutan peralatan | C59: =SUMIF($B$3:$B$37,B59,$C$3:$C$37) -> 0 | D59: =SUMIF($B$3:$B$37,B59,$D$3:$D$37) -> 0 | E59: =SUMIF($G$3:$G$14,$B59,$H$3:$H$14) -> 600000 | F59: =SUMIF($G$3:$G$14,B59,$I$3:$I$14) -> 0 | G59: =(C59+E59)-(D59+F59) -> 600000 | H59: 0
B60: Akumulasi penyusutan peralatan | C60: =SUMIF($B$3:$B$37,B60,$C$3:$C$37) -> 0 | D60: =SUMIF($B$3:$B$37,B60,$D$3:$D$37) -> 0 | E60: =SUMIF($G$3:$G$14,$B60,$H$3:$H$14) -> 0 | F60: =SUMIF($G$3:$G$14,B60,$I$3:$I$14) -> 600000 | G60: 0 | H60: =(D60+F60)-C60+E60 -> 600000
B61: Beban Perlengkapan | C61: =SUMIF($B$3:$B$37,B61,$C$3:$C$37) -> 0 | D61: =SUMIF($B$3:$B$37,B61,$D$3:$D$37) -> 0 | E61: =SUMIF($G$3:$G$14,$B61,$H$3:$H$14) -> 1300000 | F61: =SUMIF($G$3:$G$14,B61,$I$3:$I$14) -> 0 | G61: =(C61+E61)-(D61+F61) -> 1300000 | H61: 0
B62: Total | C62: =SUM(C43:C55) -> 94500000 | D62: =SUM(D43:D55) -> 94500000 | G62: =SUM(G43:G61) -> 58100000 | H62: =SUM(H43:H61) -> 58100000
B64: Income Statement
B65: Pendapatan Usaha | C65: =H49 -> 25000000
B66: Beban Usaha
B67: Beban Utilitas | C67: =G53 -> 2500000
B68: Beban Gaji | C68: =G51 -> 6500000
B69: Beban Sewa | C69: =G56 -> 3000000
B70: Beban Asuransi | C70: =G57 -> 5000000
B71: Beban Penyusutan Peralatan | C71: =G59 -> 600000
B72: Beban Perlengkapan | C72: =G61 -> 1300000
B73: Total Beban | C73: =SUM(C67:C72) -> 18900000
B74: Laba Bersih | C74: =C65-C73 -> 6100000
B76: Laporan Perubahan Modal
B77: Modal Awal | C77: =H44 -> 20000000
B78: Prive | C78: =G52 -> 1500000
B79: Laba Bersih | C79: =C74 -> 6100000
B80: Modal Akhir | C80: =(C77-C78)+C79 -> 24600000

Sheet Perincian Laporan
A1: Perincian Penyusutan Peralatan
A3: Peralatan
A4: Tanggal Perolehan | B4: Tahun | C4: Nilai Perolehan | D4: Disusutkan(Tahun) | E4: Nilai Penyusutan Pertahun
A5: 46024 | B5: 2017 | C5: =Laporan!C5 -> 3000000 | D5: 5 | E5: =C5/D5 -> 600000
A8: Total Nilai Peralatan | C8: =C5 -> 3000000
A9: Penyusutan Hingga 2017 | C9: =E5 -> 600000
A10: Nilai Buku 2017 | C10: =C8-C9 -> 2400000
A12: Perlengkapan
A13: Tanggal Perolehan | B13: Tahun | C13: Nilai Perolehan
A14: 46024 | B14: 2017 | C14: =Laporan!C6 -> 500000
A15: 46029 | B15: 2017 | C15: =Laporan!C14 -> 1000000
A16: 46045 | B16: 2017 | C16: =Laporan!C24 -> 1000000
A17: Total | C17: =SUM(C14:C16) -> 2500000
A18: Sisah Stok | C18: 1200000

Sheet Buku Besar
A1: Kas | I1: Neraca Saldo
A2: Tanggal | B2: Keterangan | C2: Ref | D2: Debit | E2: Kredit | F2: Saldo | I2: No Akun | J2: Jurnal | K2: Debit | L2: Kredit
F3: Debit | G3: Kredit | I3: 1.1 | J3: =Laporan!B43 -> Kas | K3: =F16 -> 23500000
A4: 42736 | B4: Setoran Awal | C4: JU | D4: 20000000 | F4: =D4-E4 -> 20000000 | I4: 1.2 | J4: =Laporan!B48 -> Piutang | K4: =F26 -> 3000000
A5: 42737 | B5: Pembelian Peralatan dan Perlengkapan | C5: JU | E5: 3500000 | F5: =F4+D5-E5 -> 16500000 | I5: 1.3 | J5: =Laporan!B46 -> Perlengkapan | K5: =F34 -> 1200000
A6: 42737 | B6: Pembayaran Sewa Dibayar Dimuka | C6: JU | E6: 3000000 | F6: =F5+D6-E6 -> 13500000 | I6: 1.5 | J6: =Laporan!B54 -> Asuransi Dibayar Dimuka | K6: =F40 -> 7000000
A7: 42744 | B7: Menerima Piutang | C7: JU | D7: 3000000 | F7: =F6+D7-E7 -> 16500000 | I7: 1.6 | J7: =Laporan!B47 -> Sewa Dibayar Dimuka | K7: =F46 -> 0
A8: 42756 | B8: Menerima Pendapatan | C8: JU | D8: 4000000 | F8: =F7+D8-E8 -> 20500000 | I8: 1.7 | J8: =Laporan!B45 -> Peralatan | K8: =F51 -> 3000000
A9: 42757 | B9: Menerima Piutang | C9: JU | D9: 5000000 | F9: =F8+D9-E9 -> 25500000 | I9: 1.7.1 | J9: =Laporan!B60 -> Akumulasi penyusutan peralatan | L9: =G56 -> 600000
A10: 42758 | B10: Pembelian Perlengkapan | C10: JU | E10: 1000000 | F10: =F9+D10-E10 -> 24500000 | I10: 2.1 | J10: =Laporan!B50 -> Hutang | L10: =G61 -> 1000000
A11: 42759 | B11: Menerima Piutang | C11: JU | D11: 6000000 | F11: =F10+D11-E11 -> 30500000 | I11: 2.2 | J11: =Laporan!B55 -> Pendapatan Diterima Dimuka | L11: =G67 -> 8000000
A12: 42760 | B12: Membayar Biaya Gaji | C12: JU | E12: 3000000 | F12: =F11+D12-E12 -> 27500000 | I12: 2.3 | J12: =Laporan!B58 -> Hutang Gaji | L12: =G72 -> 3500000
A13: 42761 | B13: Pengambilan Prive | C13: JU | E13: 1500000 | F13: =F12+D13-E13 -> 26000000 | I13: 3.1 | J13: =Laporan!B44 -> Modal | L13: =G79 -> 24600000
A14: 42763 | B14: Membayar Biaya Utilitas | C14: JU | E14: 2500000 | F14: =F13+D14-E14 -> 23500000 | I14: 3.2 | J14: =Laporan!B52 -> Prive | K14: =F85 -> 0
A15: 42948 | B15: Membayar Asuransi Dibayar Dimuka | C15: JU | E15: 12000000 | F15: =F14+D15-E15 -> 11500000 | I15: 4.1 | J15: =Laporan!B49 -> Pendapatan | L15: =G95 -> 0
A16: 42979 | B16: Menerima Pendapatan Diterima Dimuka | C16: JU | D16: 12000000 | F16: =F15+D16-E16 -> 23500000 | I16: 5.1 | J16: =Laporan!B53 -> Beban Utilitas | K16: =F101 -> 0
I17: 5.2 | J17: =Laporan!B51 -> Beban Gaji | K17: =F108 -> 0
A18: Piutang | I18: 5.3 | J18: =Laporan!B56 -> Beban Sewa | K18: =F114 -> 0
A19: Tanggal | B19: Keterangan | C19: Ref | D19: Debit | E19: Kredit | F19: Saldo | I19: 5.4 | J19: =Laporan!B57 -> Beban Asuransi | K19: =F120 -> 0
F20: Debit | G20: Kredit | I20: 5.5 | J20: =Laporan!B59 -> Beban penyusutan peralatan | K20: =F126 -> 0
A21: 42738 | B21: Piutang Cat Mobil Pak Joko | C21: JU | D21: 5000000 | F21: =D21-E21 -> 5000000 | I21: 5.6 | J21: =Laporan!B61 -> Beban Perlengkapan | K21: =F132 -> 0
A22: 42741 | B22: Piutang Pak Agung | C22: JU | D22: 3000000 | F22: =F21+D22-E22 -> 8000000 | J22: Ikhtisar Laba Rugi | L22: =G139 -> 0
A23: 42744 | B23: Piutang Orderan Job | C23: JU | D23: 9000000 | F23: =F22+D23-E23 -> 17000000 | K23: =SUM(K3:K22) -> 37700000 | L23: =SUM(L3:L22) -> 37700000
A24: 42744 | B24: Piutang Tanggal 9 Jan 2017 Dibayar | C24: JU | E24: 3000000 | F24: =F23+D24-E24 -> 14000000
A25: 42757 | B25: Piutang Tanggal 3 Jan 2017 Dibayar | C25: JU | E25: 5000000 | F25: =F24+D25-E25 -> 9000000
A26: 42759 | B26: Piutang Tanggal 9 Jan 2017 Dibayar | C26: JU | E26: 6000000 | F26: =F25+D26-E26 -> 3000000
A28: Perlengkapan
A29: Tanggal | B29: Keterangan | C29: Ref | D29: Debit | E29: Kredit | F29: Saldo
F30: Debit | G30: Kredit
A31: 42737 | B31: Pembelian Perlengkapan Secara Tunai | C31: JU | D31: 500000 | F31: =D31-E31 -> 500000
A32: 42742 | B32: Pembelian Perlengkapan Dibayar Akhir Bulan | C32: JU | D32: 1000000 | F32: =F31+D32-E32 -> 1500000
A33: 42758 | B33: Pembelian Perlengkapan Secara Tunai | C33: JU | D33: 1000000 | F33: =F32+D33-E33 -> 2500000
A34: 43100 | B34: Penyesuaaian Perlengkapan | C34: AJP | E34: 1300000 | F34: =F33+D34-E34 -> 1200000
A36: Asuransi Dibayar Dimuka
A37: Tanggal | B37: Keterangan | C37: Ref | D37: Debit | E37: Kredit | F37: Saldo
F38: Debit | G38: Kredit
A39: 42948 | B39: Pembayaran Asuransi Dibayar Dimuka Secara Tunai | C39: JU | D39: 12000000 | F39: =D39-E39 -> 12000000
A40: 43100 | B40: Penyesuaian Asuransi Dibayar Dimuka | C40: AJP | E40: 5000000 | F40: =F39+D40-E40 -> 7000000
A42: Sewa Dibayar Dimuka
A43: Tanggal | B43: Keterangan | C43: Ref | D43: Debit | E43: Kredit | F43: Saldo
F44: Debit | G44: Kredit
A45: 42737 | B45: Pembayaran Sewa Dibayar Dimuka | C45: JU | D45: 3000000 | F45: =D45-E45 -> 3000000
A46: 43100 | B46: Penyesuaian Sewa Dibayar Dimuka | C46: AJP | E46: 3000000 | F46: =F45+D46-E46 -> 0
A48: Peralatan
A49: Tanggal | B49: Keterangan | C49: Ref | D49: Debit | E49: Kredit | F49: Saldo
F50: Debit | G50: Kredit
A51: 42737 | B51: Pembelian Peralatan | C51: JU | D51: 3000000 | F51: =D51-E51 -> 3000000
A53: Akumulasi Penyusutan Peralatan
A54: Tanggal | B54: Keterangan | C54: Ref | D54: Debit | E54: Kredit | F54: Saldo
F55: Debit | G55: Kredit
A56: 43100 | B56: Penyesuaian Penyusutan Peralatan | C56: AJP | E56: 600000 | G56: =E56-D56 -> 600000
A58: Hutang Usaha
A59: Tanggal | B59: Keterangan | C59: Ref | D59: Debit | E59: Kredit | F59: Saldo
F60: Debit | G60: Kredit
A61: 42742 | B61: Hutang Perlengkapan Bengkel Toko Agung | C61: JU | E61: 1000000 | G61: =E61-D61 -> 1000000
A63: Pendapatan Diterima Dimuka
A64: Tanggal | B64: Keterangan | C64: Ref | D64: Debit | E64: Kredit | F64: Saldo
F65: Debit | G65: Kredit
A66: 42744 | B66: Menerima Pendapatan Diterima Dimuka | C66: JU | E66: 12000000 | G66: =E66-D66 -> 12000000
A67: 43100 | B67: Penyesuaian Pendapatan Diterima Dimuka | C67: AJP | D67: 4000000 | G67: =G66+E67-D67 -> 8000000
A69: Hutang Gaji
A70: Tanggal | B70: Keterangan | C70: Ref | D70: Debit | E70: Kredit | F70: Saldo
F71: Debit | G71: Kredit
A72: 43100 | B72: Penyesuaian Atas Gaji Desember | C72: AJP | E72: 3500000 | G72: =E72-D72 -> 3500000
A74: Modal
A75: Tanggal | B75: Keterangan | C75: Ref | D75: Debit | E75: Kredit | F75: Saldo
F76: Debit | G76: Kredit
A77: 42736 | B77: Setoran Awal | C77: JU | E77: 20000000 | G77: =E77-D77 -> 20000000
A78: 43100 | B78: Penyesuaian Jurnal Penutup | C78: JP | E78: ='Jurnal Penutup'!D15 -> 6100000 | G78: =G77+E78-D78 -> 26100000
A79: 43100 | B79: Penyesuaian Jurnal Penutup | C79: JP | D79: ='Jurnal Penutup'!C17 -> 1500000 | G79: =G78+E79-D79 -> 24600000
A81: Prive
A82: Tanggal | B82: Keterangan | C82: Ref | D82: Debit | E82: Kredit | F82: Saldo
F83: Debit | G83: Kredit
A84: 42736 | B84: Penarikan Prive | C84: JU | D84: 1500000 | F84: =D84-E84 -> 1500000
A85: 43100 | B85: Penyesuaian Jurnal Penutup | C85: JP | E85: ='Jurnal Penutup'!D18 -> 1500000 | F85: =F84+D85-E85 -> 0
A87: Pendapatan Usaha
A88: Tanggal | B88: Keterangan | C88: Ref | D88: Debit | E88: Kredit | F88: Saldo
F89: Debit | G89: Kredit
A90: 42738 | B90: Pendapatan Dari Pak Joko | C90: JU | E90: 5000000 | G90: =E90-D90 -> 5000000
A91: 42741 | B91: Pendapatan Dari Pak Agung | C91: JU | E91: 3000000 | G91: =G90+E91-D91 -> 8000000
A92: 42744 | B92: Pendapatan Diterima | C92: JU | E92: 9000000 | G92: =G91+E92-D92 -> 17000000
A93: 42756 | B93: Pendapatan Diterima | C93: JU | E93: 4000000 | G93: =G92+E93-D93 -> 21000000
A94: 43100 | B94: Penyesuaian Pendapatan Diterima Dimuka | C94: AJP | E94: 4000000 | G94: =G93+E94-D94 -> 25000000
A95: 43100 | B95: Penyesuaian Jurnal Penutup | C95: JP | D95: ='Jurnal Penutup'!C3 -> 25000000 | G95: =G94+E95-D95 -> 0
A97: Biaya Utilitas
A98: Tanggal | B98: Keterangan | C98: Ref | D98: Debit | E98: Kredit | F98: Saldo
F99: Debit | G99: Kredit
A100: 42763 | B100: Membayar Uang Listrik dan Telepon | C100: JU | D100: 2500000 | F100: =D100-E100 -> 2500000
A101: 43100 | B101: Penyesuaian Jurnal Penutup | C101: JP | E101: ='Jurnal Penutup'!D7 -> 2500000 | F101: =F100+D101-E101 -> 0
A103: Beban Gaji
A104: Tanggal | B104: Keterangan | C104: Ref | D104: Debit | E104: Kredit | F104: Saldo
F105: Debit | G105: Kredit
A106: 42760 | B106: Membayar Biaya Gaji | C106: JU | D106: 3000000 | F106: =D106-E106 -> 3000000
A107: 43100 | B107: Penyesuaian Gaji Karyawan Bulan Desember | C107: AJP | D107: 3500000 | F107: =F106+D107-E107 -> 6500000
A108: 43100 | B108: Penyesuaian Jurnal Penutup | C108: JP | E108: ='Jurnal Penutup'!D8 -> 6500000 | F108: =F107+D108-E108 -> 0
A110: Beban Sewa
A111: Tanggal | B111: Keterangan | C111: Ref | D111: Debit | E111: Kredit | F111: Saldo
F112: Debit | G112: Kredit
A113: 43100 | B113: Penyesuaian Sewa Dibayar Dimuka | C113: AJP | D113: 3000000 | F113: =D113-E113 -> 3000000
A114: 43100 | B114: Penyesuaian Jurnal Penutup | C114: JP | E114: ='Jurnal Penutup'!D9 -> 3000000 | F114: =F113+D114-E114 -> 0
...

Sheet Buku Besar Pembantu
A1: Pembantu Piutang
A3: Pak Joko
A4: Tanggal | B4: Keterangan | C4: Ref | D4: Debit | E4: Kredit | F4: Saldo
F5: Debit | G5: Kredit
A6: 42738 | B6: Menerima Piutang | C6: JU | D6: 5000000 | F6: =D6-E6 -> 5000000
A7: 42757 | B7: Pelunasan Piutang | C7: JU | E7: 5000000 | F7: =F6+D7-E7 -> 0
A9: Pak Agung
A10: Tanggal | B10: Keterangan | C10: Ref | D10: Debit | E10: Kredit | F10: Saldo
F11: Debit | G11: Kredit
A12: 42741 | B12: Menerima Piutang | C12: JU | D12: 3000000 | F12: =D12-E12 -> 3000000
A14: Orderan
A15: Tanggal | B15: Keterangan | C15: Ref | D15: Debit | E15: Kredit | F15: Saldo
F16: Debit | G16: Kredit
A17: 42744 | B17: Menerima Piutang | C17: JU | D17: 9000000 | F17: =D17-E17 -> 9000000
A18: 42744 | B18: Pelunasan Piutang | C18: JU | E18: 3000000 | F18: =F17+D18-E18 -> 6000000
A19: 42759 | B19: Pelunasan Piutang | C19: JU | E19: 6000000 | F19: =F18+D19-E19 -> 0

Sheet Jurnal Penutup
A1: Jurnal Penutup
A2: Tanggal | B2: Nama Akun | C2: Debit | D2: Credit
A3: 43100 | B3: Pendapatan Usaha | C3: =Laporan!C65 -> 25000000
B4: Ikhtisar Laba Rugi | D4: =Laporan!C65 -> 25000000
B6: Ikhtisar Laba Rugi | C6: =SUM(D7:D12) -> 18900000
B7: Beban Utilitas | D7: =Laporan!C67 -> 2500000
B8: Beban Gaji | D8: =Laporan!C68 -> 6500000
B9: Beban Sewa | D9: =Laporan!C69 -> 3000000
B10: Beban Asuransi | D10: =Laporan!C70 -> 5000000
B11: Beban Penyusutan Peralatan | D11: =Laporan!C71 -> 600000
B12: Beban Perlengkapan | D12: =Laporan!C72 -> 1300000
B14: Ikhtisar Laba Rugi | C14: =Laporan!C74 -> 6100000
B15: Modal | D15: =Laporan!C74 -> 6100000
B17: Modal | C17: =Laporan!G52 -> 1500000
B18: Prive | D18: =Laporan!G52 -> 1500000
C19: =SUM(C3:C18) -> 51500000 | D19: =SUM(D3:D18) -> 51500000

Sheet Neraca Awal Periode Baru
A1: Neraca Saldo (Balance Sheet)
A2: Awal Periode 2018
A3: Aktiva(Assets) | D3: Passiva
A4: Aktiva Lancar | D4: Hutang
A5: Kas | B5: ='Buku Besar'!K3 -> 23500000 | D5: Hutang Lancar
A6: Piutang | B6: ='Buku Besar'!K4 -> 3000000 | D6: Hutang Usaha | E6: ='Buku Besar'!L10 -> 1000000
A7: Perlengkapan | B7: ='Buku Besar'!K5 -> 1200000 | D7: Pendapatan Diterima Dimuka | E7: ='Buku Besar'!L11 -> 8000000
A8: Asuransi Dibayar Dimuka | B8: ='Buku Besar'!K6 -> 7000000 | D8: Hutang Gaji | E8: ='Buku Besar'!L12 -> 3500000
A9: Sewa Dibayar Dimuka | B9: ='Buku Besar'!K7 -> 0 | D9: Hutang Jangka Panjang
A10: Total Aktiva Lancar | C10: =SUM(B5:B9) -> 34700000 | D10: Hutang Bank | E10: 0
A11: Aktiva Tetap | D11: Total Utang | F11: =SUM(E5:E10) -> 12500000
A12: Tanah
A13: Bangunan | D13: Modal | F13: ='Buku Besar'!L13 -> 24600000
A14: Akumulasi Penyusutan Bangunan
A15: Peralatan | B15: ='Buku Besar'!K8 -> 3000000
A16: Akumulasi Penyusutan Peralatan | C16: =-'Buku Besar'!L9 -> -600000
A17: Total Aktiva Tetap | C17: =SUM(SUM(B12:B16),SUM(C12:C16)) -> 2400000
A18: Total Aktiva | C18: =C10+C17 -> 37100000 | D18: Total Utang & Modal | F18: =F11+F13 -> 37100000
